{
  "main": [
    {
      "enable": true,
      "name": "Accueil",
      "url": "/"
    },
    {
      "enable": true,
      "name": "Solutions",
      "hasMegaMenu": true,
      "menus": [
        {
          "enable": true,
          "name": "Produits",
          "children": [
            {
              "enable": true,
              "name": "Data:pipe",
              "url": "/services/products/"
                },
                {
                  "enable": true,
              "name": "Analyt:ix",
              "url": "/services/products/"
                },
                {
              "enable": true,
              "name": "eLea:rn",
              "url": "/services/products/"
            },
            {
              "enable": true,
              "name": "Pre:dict",
              "url": "/services/products/"
            }
          ]
        },
        {
          "enable": true,
          "name": "Services",
          "children": [
            {
              "enable": true,
              "name": "Atelier de Découverte Stratégique",
              "url": "/services/services/"
                },
                {
                  "enable": true,
              "name": "Consultation",
              "url": "/services/services/"
            },
            {
              "enable": true,
              "name": "Formation",
              "url": "/services/services/"
            },
            {
              "enable": true,
              "name": "Certification SBI",
              "url": "/services/packages/"
            }
          ]
        },
        {
          "enable": true,
          "name": "Packages",
          "children": [
            {
              "enable": true,
              "name": "SBI Care KIT",
              "url": "/services/packages/"
            },
            {
              "enable": true,
              "name": "SBI Research KIT",
              "url": "/services/packages/"
            }
          ]
        }
      ]
    },
    {
      "enable": true,
      "name": "Contact",
      "url": "/contact/"
    },
    {
      "enable": true,
      "name": "À propos",
      "url": "/about/"
    }
  ],
  "footer_menu": [
    {
      "enable": true,
      "name": "Conditions d'utilisation",
      "url": "/terms-conditions/"
    },
    {
      "enable": true,
      "name": "Politique de confidentialité",
      "url": "/privacy-policy/"
    }
  ],
  "footer_menu_quick_link": [
    {
      "enable": true,
      "name": "Accueil",
      "url": "/"
    },
    {
      "enable": true,
      "name": "À propos de nous",
      "url": "/about/"
    },
    {
      "enable": true,
      "name": "Contactez-nous",
      "url": "/contact/"
    }
  ],
  "footer_menu_resources": [
    {
      "enable": true,
      "name": "Data:pipe",
      "url": "/services/products/"
    },
    {
      "enable": true,
      "name": "Analyt:ix",
      "url": "/services/products/"
    },
    {
      "enable": true,
      "name": "eLea:rn",
      "url": "/services/products/"
    },
    {
      "enable": true,
      "name": "Atelier de Découverte",
      "url": "/services/"
    }
  ],
  "footer_menu_legal": [
    {
      "enable": true,
      "name": "Conditions d'utilisation",
      "url": "/terms-conditions/"
    },
    {
      "enable": true,
      "name": "Politique de confidentialité",
      "url": "/privacy-policy/"
    }
  ]
}
